[{
  "kind": "Listing",
  "data": {
    "modhash": "hl16s2rizwb13275ba68d8d0b1b11dd63d052aae578c39e66c",
    "children": [{
      "kind": "t3",
      "data": {
        "domain": "self.til",
        "banned_by": null,
        "media_embed": {},
        "subreddit": "til",
        "selftext_html": "&lt;!-- SC_OFF --&gt;&lt;div class=\"md\"&gt;&lt;p&gt;Everything is the same, just a different subreddit (with explicit rules).&lt;/p&gt;\n&lt;/div&gt;&lt;!-- SC_ON --&gt;",
        "selftext": "Everything is the same, just a different subreddit (with explicit rules).",
        "likes": null,
        "user_reports": [],
        "secure_media": null,
        "link_flair_text": null,
        "id": "hh3eb",
        "gilded": 0,
        "archived": true,
        "clicked": false,
        "report_reasons": null,
        "author": "roger_",
        "num_comments": 15,
        "score": 76,
        "approved_by": null,
        "over_18": false,
        "hidden": false,
        "thumbnail": "self",
        "subreddit_id": "t5_2qq9h",
        "edited": true,
        "link_flair_css_class": null,
        "author_flair_css_class": null,
        "downs": 0,
        "mod_reports": [],
        "secure_media_embed": {},
        "saved": false,
        "is_self": true,
        "name": "t3_hh3eb",
        "permalink": "/r/til/comments/hh3eb/rtil_is_no_more_please_use_rtodayilearned_instead/",
        "stickied": true,
        "created": 1306039247.0,
        "url": "http://www.reddit.com/r/til/comments/hh3eb/rtil_is_no_more_please_use_rtodayilearned_instead/",
        "author_flair_text": null,
        "title": "r/TIL is no more. Please use r/TodayILearned instead",
        "created_utc": 1306035647.0,
        "ups": 76,
        "upvote_ratio": 0.86,
        "media": null,
        "visited": false,
        "num_reports": null,
        "distinguished": "moderator"
      }
    }],
    "after": null,
    "before": null
  }
}, {
  "kind": "Listing",
  "data": {
    "modhash": "hl16s2rizwb13275ba68d8d0b1b11dd63d052aae578c39e66c",
    "children": [{
      "kind": "t1",
      "data": {
        "subreddit_id": "t5_2qq9h",
        "banned_by": null,
        "link_id": "t3_hh3eb",
        "likes": null,
        "replies": {
          "kind": "Listing",
          "data": {
            "modhash": "hl16s2rizwb13275ba68d8d0b1b11dd63d052aae578c39e66c",
            "children": [{
              "kind": "more",
              "data": {
                "count": 1,
                "parent_id": "t1_c1vd1eg",
                "children": ["c30mfl7"],
                "id": "c30mfl7",
                "name": "t1_c30mfl7"
              }
            }],
            "after": null,
            "before": null
          }
        },
        "user_reports": [],
        "saved": false,
        "id": "c1vd1eg",
        "gilded": 0,
        "archived": true,
        "report_reasons": null,
        "author": "the8thbit",
        "parent_id": "t3_hh3eb",
        "score": 16,
        "approved_by": null,
        "controversiality": 0,
        "body": "TIL TIL is dead",
        "edited": false,
        "author_flair_css_class": null,
        "downs": 0,
        "body_html": "&lt;div class=\"md\"&gt;&lt;p&gt;TIL TIL is dead&lt;/p&gt;\n&lt;/div&gt;",
        "subreddit": "til",
        "score_hidden": false,
        "name": "t1_c1vd1eg",
        "created": 1306051241.0,
        "author_flair_text": null,
        "created_utc": 1306047641.0,
        "ups": 16,
        "mod_reports": [],
        "num_reports": null,
        "distinguished": null
      }
    }, {
      "kind": "t1",
      "data": {
        "subreddit_id": "t5_2qq9h",
        "banned_by": null,
        "link_id": "t3_hh3eb",
        "likes": null,
        "replies": {
          "kind": "Listing",
          "data": {
            "modhash": "hl16s2rizwb13275ba68d8d0b1b11dd63d052aae578c39e66c",
            "children": [{
              "kind": "t1",
              "data": {
                "subreddit_id": "t5_2qq9h",
                "banned_by": null,
                "link_id": "t3_hh3eb",
                "likes": null,
                "replies": {
                  "kind": "Listing",
                  "data": {
                    "modhash": "hl16s2rizwb13275ba68d8d0b1b11dd63d052aae578c39e66c",
                    "children": [{
                      "kind": "t1",
                      "data": {
                        "subreddit_id": "t5_2qq9h",
                        "banned_by": null,
                        "link_id": "t3_hh3eb",
                        "likes": null,
                        "replies": {
                          "kind": "Listing",
                          "data": {
                            "modhash": "hl16s2rizwb13275ba68d8d0b1b11dd63d052aae578c39e66c",
                            "children": [{
                              "kind": "t1",
                              "data": {
                                "subreddit_id": "t5_2qq9h",
                                "banned_by": null,
                                "link_id": "t3_hh3eb",
                                "likes": null,
                                "replies": "",
                                "user_reports": [],
                                "saved": false,
                                "id": "c1vfzaf",
                                "gilded": 0,
                                "archived": true,
                                "report_reasons": null,
                                "author": "SuperBry",
                                "parent_id": "t1_c1vfww6",
                                "score": 1,
                                "approved_by": null,
                                "controversiality": 0,
                                "body": "I will just use /.compact as I like some of them. ",
                                "edited": false,
                                "author_flair_css_class": null,
                                "downs": 0,
                                "body_html": "&lt;div class=\"md\"&gt;&lt;p&gt;I will just use /.compact as I like some of them. &lt;/p&gt;\n&lt;/div&gt;",
                                "subreddit": "til",
                                "score_hidden": false,
                                "name": "t1_c1vfzaf",
                                "created": 1306104699.0,
                                "author_flair_text": null,
                                "created_utc": 1306101099.0,
                                "distinguished": null,
                                "mod_reports": [],
                                "num_reports": null,
                                "ups": 1
                              }
                            }],
                            "after": null,
                            "before": null
                          }
                        },
                        "user_reports": [],
                        "saved": false,
                        "id": "c1vfww6",
                        "gilded": 0,
                        "archived": true,
                        "report_reasons": null,
                        "author": "neptath",
                        "parent_id": "t1_c1ve8xy",
                        "score": 3,
                        "approved_by": null,
                        "controversiality": 0,
                        "body": "[reddit.com/prefs](reddit.com/prefs)&gt;uncheck \"allow reddits to show me custom styles\"&gt;Submit&gt;???&gt;Profit!",
                        "edited": false,
                        "author_flair_css_class": null,
                        "downs": 0,
                        "body_html": "&lt;div class=\"md\"&gt;&lt;p&gt;[reddit.com/prefs](reddit.com/prefs)&amp;gt;uncheck &amp;quot;allow reddits to show me custom styles&amp;quot;&amp;gt;Submit&amp;gt;???&amp;gt;Profit!&lt;/p&gt;\n&lt;/div&gt;",
                        "subreddit": "til",
                        "score_hidden": false,
                        "name": "t1_c1vfww6",
                        "created": 1306103872.0,
                        "author_flair_text": null,
                        "created_utc": 1306100272.0,
                        "ups": 3,
                        "mod_reports": [],
                        "num_reports": null,
                        "distinguished": null
                      }
                    }, {
                      "kind": "t1",
                      "data": {
                        "subreddit_id": "t5_2qq9h",
                        "banned_by": null,
                        "link_id": "t3_hh3eb",
                        "likes": null,
                        "replies": "",
                        "user_reports": [],
                        "saved": false,
                        "id": "c1ve96o",
                        "gilded": 0,
                        "archived": true,
                        "report_reasons": null,
                        "author": "Maxion",
                        "parent_id": "t1_c1ve8xy",
                        "score": 2,
                        "approved_by": null,
                        "controversiality": 0,
                        "body": "Mwahahahahah",
                        "edited": false,
                        "author_flair_css_class": null,
                        "downs": 0,
                        "body_html": "&lt;div class=\"md\"&gt;&lt;p&gt;Mwahahahahah&lt;/p&gt;\n&lt;/div&gt;",
                        "subreddit": "til",
                        "score_hidden": false,
                        "name": "t1_c1ve96o",
                        "created": 1306082472.0,
                        "author_flair_text": null,
                        "created_utc": 1306078872.0,
                        "ups": 2,
                        "mod_reports": [],
                        "num_reports": null,
                        "distinguished": null
                      }
                    }],
                    "after": null,
                    "before": null
                  }
                },
                "user_reports": [],
                "saved": false,
                "id": "c1ve8xy",
                "gilded": 0,
                "archived": true,
                "report_reasons": null,
                "author": "roger_",
                "parent_id": "t1_c1ve8pj",
                "score": 3,
                "approved_by": null,
                "controversiality": 0,
                "body": "Good luck with that :)",
                "edited": false,
                "author_flair_css_class": null,
                "downs": 0,
                "body_html": "&lt;div class=\"md\"&gt;&lt;p&gt;Good luck with that :)&lt;/p&gt;\n&lt;/div&gt;",
                "subreddit": "til",
                "score_hidden": false,
                "name": "t1_c1ve8xy",
                "created": 1306082366.0,
                "author_flair_text": null,
                "created_utc": 1306078766.0,
                "distinguished": null,
                "mod_reports": [],
                "num_reports": null,
                "ups": 3
              }
            }],
            "after": null,
            "before": null
          }
        },
        "user_reports": [],
        "saved": false,
        "id": "c1ve8pj",
        "gilded": 0,
        "archived": true,
        "report_reasons": null,
        "author": "Maxion",
        "parent_id": "t3_hh3eb",
        "score": 8,
        "approved_by": null,
        "controversiality": 0,
        "body": "I shall continue submitting to /r/til/ \n\nSome custom stylesheet won't stop me!",
        "edited": false,
        "author_flair_css_class": null,
        "downs": 0,
        "body_html": "&lt;div class=\"md\"&gt;&lt;p&gt;I shall continue submitting to &lt;a href=\"/r/til/\"&gt;/r/til/&lt;/a&gt; &lt;/p&gt;\n\n&lt;p&gt;Some custom stylesheet won&amp;#39;t stop me!&lt;/p&gt;\n&lt;/div&gt;",
        "subreddit": "til",
        "score_hidden": false,
        "name": "t1_c1ve8pj",
        "created": 1306082271.0,
        "author_flair_text": null,
        "created_utc": 1306078671.0,
        "ups": 8,
        "mod_reports": [],
        "num_reports": null,
        "distinguished": null
      }
    }, {
      "kind": "t1",
      "data": {
        "subreddit_id": "t5_2qq9h",
        "banned_by": null,
        "link_id": "t3_hh3eb",
        "likes": null,
        "replies": "",
        "user_reports": [],
        "saved": false,
        "id": "c1vfcjv",
        "gilded": 0,
        "archived": true,
        "report_reasons": null,
        "author": "anyletter",
        "parent_id": "t3_hh3eb",
        "score": 3,
        "approved_by": null,
        "controversiality": 0,
        "body": "I prefer r/til because of the tighter community. ",
        "edited": false,
        "author_flair_css_class": null,
        "downs": 0,
        "body_html": "&lt;div class=\"md\"&gt;&lt;p&gt;I prefer r/til because of the tighter community. &lt;/p&gt;\n&lt;/div&gt;",
        "subreddit": "til",
        "score_hidden": false,
        "name": "t1_c1vfcjv",
        "created": 1306096951.0,
        "author_flair_text": null,
        "created_utc": 1306093351.0,
        "ups": 3,
        "mod_reports": [],
        "num_reports": null,
        "distinguished": null
      }
    }, {
      "kind": "t1",
      "data": {
        "subreddit_id": "t5_2qq9h",
        "banned_by": null,
        "link_id": "t3_hh3eb",
        "likes": null,
        "replies": {
          "kind": "Listing",
          "data": {
            "modhash": "hl16s2rizwb13275ba68d8d0b1b11dd63d052aae578c39e66c",
            "children": [{
              "kind": "t1",
              "data": {
                "subreddit_id": "t5_2qq9h",
                "banned_by": null,
                "link_id": "t3_hh3eb",
                "likes": null,
                "replies": {
                  "kind": "Listing",
                  "data": {
                    "modhash": "hl16s2rizwb13275ba68d8d0b1b11dd63d052aae578c39e66c",
                    "children": [{
                      "kind": "t1",
                      "data": {
                        "subreddit_id": "t5_2qq9h",
                        "banned_by": null,
                        "link_id": "t3_hh3eb",
                        "likes": null,
                        "replies": "",
                        "user_reports": [],
                        "saved": false,
                        "id": "c1yyohm",
                        "gilded": 0,
                        "archived": true,
                        "report_reasons": null,
                        "author": "[deleted]",
                        "parent_id": "t1_c1y7vyv",
                        "score": 3,
                        "approved_by": null,
                        "controversiality": 0,
                        "body": "But why just why ? I loved it here.... Today I learned is a bunch of crap",
                        "edited": false,
                        "author_flair_css_class": null,
                        "downs": 0,
                        "body_html": "&lt;div class=\"md\"&gt;&lt;p&gt;But why just why ? I loved it here.... Today I learned is a bunch of crap&lt;/p&gt;\n&lt;/div&gt;",
                        "subreddit": "til",
                        "score_hidden": false,
                        "name": "t1_c1yyohm",
                        "created": 1307738372.0,
                        "author_flair_text": null,
                        "created_utc": 1307734772.0,
                        "ups": 3,
                        "mod_reports": [],
                        "num_reports": null,
                        "distinguished": null
                      }
                    }],
                    "after": null,
                    "before": null
                  }
                },
                "user_reports": [],
                "saved": false,
                "id": "c1y7vyv",
                "gilded": 0,
                "archived": true,
                "report_reasons": null,
                "author": "roger_",
                "parent_id": "t1_c1y7vkw",
                "score": 3,
                "approved_by": null,
                "controversiality": 0,
                "body": "We just added some CSS code for the redirection and made it protected so no one can post.",
                "edited": false,
                "author_flair_css_class": null,
                "downs": 0,
                "body_html": "&lt;div class=\"md\"&gt;&lt;p&gt;We just added some CSS code for the redirection and made it protected so no one can post.&lt;/p&gt;\n&lt;/div&gt;",
                "subreddit": "til",
                "score_hidden": false,
                "name": "t1_c1y7vyv",
                "created": 1307421007.0,
                "author_flair_text": null,
                "created_utc": 1307417407.0,
                "distinguished": null,
                "mod_reports": [],
                "num_reports": null,
                "ups": 3
              }
            }],
            "after": null,
            "before": null
          }
        },
        "user_reports": [],
        "saved": false,
        "id": "c1y7vkw",
        "gilded": 0,
        "archived": true,
        "report_reasons": null,
        "author": "wepo",
        "parent_id": "t3_hh3eb",
        "score": 3,
        "approved_by": null,
        "controversiality": 0,
        "body": "How can you effectively close a subreddit?   \n\nGenuinely curious.  Never seen it done before.",
        "edited": false,
        "author_flair_css_class": null,
        "downs": 0,
        "body_html": "&lt;div class=\"md\"&gt;&lt;p&gt;How can you effectively close a subreddit?   &lt;/p&gt;\n\n&lt;p&gt;Genuinely curious.  Never seen it done before.&lt;/p&gt;\n&lt;/div&gt;",
        "subreddit": "til",
        "score_hidden": false,
        "name": "t1_c1y7vkw",
        "created": 1307420894.0,
        "author_flair_text": null,
        "created_utc": 1307417294.0,
        "ups": 3,
        "mod_reports": [],
        "num_reports": null,
        "distinguished": null
      }
    }, {
      "kind": "t1",
      "data": {
        "subreddit_id": "t5_2qq9h",
        "banned_by": null,
        "link_id": "t3_hh3eb",
        "likes": null,
        "replies": "",
        "user_reports": [],
        "saved": false,
        "id": "c2qgffk",
        "gilded": 0,
        "archived": true,
        "report_reasons": null,
        "author": "virusporn",
        "parent_id": "t3_hh3eb",
        "score": 2,
        "approved_by": null,
        "controversiality": 0,
        "body": "No custom style shall stop me commenting!",
        "edited": false,
        "author_flair_css_class": null,
        "downs": 0,
        "body_html": "&lt;div class=\"md\"&gt;&lt;p&gt;No custom style shall stop me commenting!&lt;/p&gt;\n&lt;/div&gt;",
        "subreddit": "til",
        "score_hidden": false,
        "name": "t1_c2qgffk",
        "created": 1318300931.0,
        "author_flair_text": null,
        "created_utc": 1318297331.0,
        "ups": 2,
        "mod_reports": [],
        "num_reports": null,
        "distinguished": null
      }
    }, {
      "kind": "t1",
      "data": {
        "subreddit_id": "t5_2qq9h",
        "banned_by": null,
        "link_id": "t3_hh3eb",
        "likes": null,
        "replies": {
          "kind": "Listing",
          "data": {
            "modhash": "hl16s2rizwb13275ba68d8d0b1b11dd63d052aae578c39e66c",
            "children": [{
              "kind": "t1",
              "data": {
                "subreddit_id": "t5_2qq9h",
                "banned_by": null,
                "link_id": "t3_hh3eb",
                "likes": null,
                "replies": {
                  "kind": "Listing",
                  "data": {
                    "modhash": "hl16s2rizwb13275ba68d8d0b1b11dd63d052aae578c39e66c",
                    "children": [{
                      "kind": "t1",
                      "data": {
                        "subreddit_id": "t5_2qq9h",
                        "banned_by": null,
                        "link_id": "t3_hh3eb",
                        "likes": null,
                        "replies": "",
                        "user_reports": [],
                        "saved": false,
                        "id": "c23y9s7",
                        "gilded": 0,
                        "archived": true,
                        "report_reasons": null,
                        "author": "KerrickLong",
                        "parent_id": "t1_c23y3yn",
                        "score": 2,
                        "approved_by": null,
                        "controversiality": 0,
                        "body": "If you change `a[href=\"http://www.reddit.com/r/todayilearned/#newlink\"]` to `#form-t5_2qq9h8i0.usertext a[href=\"http://www.reddit.com/r/todayilearned/#newlink\"]` it will only activate it on the http://www.reddit.com/r/til/ page.",
                        "edited": false,
                        "author_flair_css_class": null,
                        "downs": 0,
                        "body_html": "&lt;div class=\"md\"&gt;&lt;p&gt;If you change &lt;code&gt;a[href=&amp;quot;http://www.reddit.com/r/todayilearned/#newlink&amp;quot;]&lt;/code&gt; to &lt;code&gt;#form-t5_2qq9h8i0.usertext a[href=&amp;quot;http://www.reddit.com/r/todayilearned/#newlink&amp;quot;]&lt;/code&gt; it will only activate it on the &lt;a href=\"http://www.reddit.com/r/til/\"&gt;http://www.reddit.com/r/til/&lt;/a&gt; page.&lt;/p&gt;\n&lt;/div&gt;",
                        "subreddit": "til",
                        "score_hidden": false,
                        "name": "t1_c23y9s7",
                        "created": 1309972130.0,
                        "author_flair_text": null,
                        "created_utc": 1309968530.0,
                        "ups": 2,
                        "mod_reports": [],
                        "num_reports": null,
                        "distinguished": null
                      }
                    }],
                    "after": null,
                    "before": null
                  }
                },
                "user_reports": [],
                "saved": false,
                "id": "c23y3yn",
                "gilded": 0,
                "archived": true,
                "report_reasons": null,
                "author": "roger_",
                "parent_id": "t1_c23xwuh",
                "score": 1,
                "approved_by": null,
                "controversiality": 0,
                "body": "You can disable custom stylesheet support in your reddit preferences to see the archives. There's no other way AFAIK.",
                "edited": false,
                "author_flair_css_class": null,
                "downs": 0,
                "body_html": "&lt;div class=\"md\"&gt;&lt;p&gt;You can disable custom stylesheet support in your reddit preferences to see the archives. There&amp;#39;s no other way AFAIK.&lt;/p&gt;\n&lt;/div&gt;",
                "subreddit": "til",
                "score_hidden": false,
                "name": "t1_c23y3yn",
                "created": 1309970733.0,
                "author_flair_text": null,
                "created_utc": 1309967133.0,
                "distinguished": null,
                "mod_reports": [],
                "num_reports": null,
                "ups": 1
              }
            }],
            "after": null,
            "before": null
          }
        },
        "user_reports": [],
        "saved": false,
        "id": "c23xwuh",
        "gilded": 0,
        "archived": true,
        "report_reasons": null,
        "author": "KerrickLong",
        "parent_id": "t3_hh3eb",
        "score": 1,
        "approved_by": null,
        "controversiality": 0,
        "body": "Can you please only enable the CSS code for the closed notice on the main subreddit page? I'd like to browse the archives.",
        "edited": false,
        "author_flair_css_class": null,
        "downs": 0,
        "body_html": "&lt;div class=\"md\"&gt;&lt;p&gt;Can you please only enable the CSS code for the closed notice on the main subreddit page? I&amp;#39;d like to browse the archives.&lt;/p&gt;\n&lt;/div&gt;",
        "subreddit": "til",
        "score_hidden": false,
        "name": "t1_c23xwuh",
        "created": 1309968966.0,
        "author_flair_text": null,
        "created_utc": 1309965366.0,
        "ups": 1,
        "mod_reports": [],
        "num_reports": null,
        "distinguished": null
      }
    }, {
      "kind": "t1",
      "data": {
        "subreddit_id": "t5_2qq9h",
        "banned_by": null,
        "link_id": "t3_hh3eb",
        "likes": null,
        "replies": "",
        "user_reports": [],
        "saved": false,
        "id": "c2cf6rv",
        "gilded": 0,
        "archived": true,
        "report_reasons": null,
        "author": "thefalcone",
        "parent_id": "t3_hh3eb",
        "score": 1,
        "approved_by": null,
        "controversiality": 0,
        "body": "Squad,  TIL IS DOWN! Regroup at r/todayilearned, hoorah? ",
        "edited": false,
        "author_flair_css_class": null,
        "downs": 0,
        "body_html": "&lt;div class=\"md\"&gt;&lt;p&gt;Squad,  TIL IS DOWN! Regroup at r/todayilearned, hoorah? &lt;/p&gt;\n&lt;/div&gt;",
        "subreddit": "til",
        "score_hidden": false,
        "name": "t1_c2cf6rv",
        "created": 1313350758.0,
        "author_flair_text": null,
        "created_utc": 1313347158.0,
        "ups": 1,
        "mod_reports": [],
        "num_reports": null,
        "distinguished": null
      }
    }],
    "after": null,
    "before": null
  }
}]